swaach_text/__init__.py
swaach_text/cleaner.py
swaach_text/cli.py
swaach_text/emoji.py
swaach_text/rules.py
swaach_text/textops.py
swaach_text-0.1.0.dist-info/METADATA
swaach_text-0.1.0.dist-info/WHEEL
swaach_text-0.1.0.dist-info/entry_points.txt
swaach_text-0.1.0.dist-info/licenses/LICENSE
swaach_text-0.1.0.dist-info/RECORD
