Metadata-Version: 2.4
Name: swaach-text
Version: 0.1.0
Summary: Hinglish + social text normalization (emoji→text, diacritics removal, hashtag splitting)
Author-email: Sanjay Kumar <you@example.com>
License: MIT
License-File: LICENSE
Keywords: cleaning,diacritics,emoji,hashtags,hinglish,nlp,normalization,text
Classifier: Intended Audience :: Developers
Classifier: License :: OSI Approved :: MIT License
Classifier: Programming Language :: Python :: 3
Classifier: Programming Language :: Python :: 3 :: Only
Classifier: Topic :: Text Processing :: Linguistic
Requires-Python: >=3.8
